cpu.v
module fetch (pc, ins);
  input [7:0] pc;   //32bitの値はでかすぎるだろ
  output [31:0] ins;
  reg [31:0] ins_mem[0:255];
  initial begin
    // $readmemb("sample34.bnr", ins_mem);
     $readmemb("/home/denjo/Documents/Assignment/arch21/computer-architecture-2021/sample35.bnr", ins_mem);
  //  $readmemb("add2.bnr", ins_mem);

  end
  assign ins = ins_mem[pc];
endmodule

module execute (clk, ins, pc, reg1, reg2, wra, result, nextpc);
	input clk;
	input [31:0] ins, pc, reg1, reg2; 
	output [4:0] wra;
	output [31:0] result, nextpc;
	wire [5:0] 	 op;
	wire [4:0] 	 shift, operation;
	wire [25:0] 	 addr;
	wire [31:0] 	 dpl_imm, operand2, alu_result, nonbranch, branch, mem_address, dm_r_data;
	wire [3:0] 	 wren;

  	function [4:0] opr_gen; 	// 出力にどんな演算結果を渡すのかを決める(加算，減算など)
		input [5:0] op;        
		input [4:0] operation;
		case (op)				//　アセンブラで指定した命令番号について場合分け
			6'd0: opr_gen = operation;
			6'd1: opr_gen = 5'd0;	// add
			6'd4: opr_gen = 5'd8;	// and
			6'd5: opr_gen = 5'd9;	// or
			6'd6: opr_gen = 5'd10;	// xor
			6'd36: opr_gen = 5'd20;  // sub, bgt0_subはop36番
			default: opr_gen = 5'h1f;
		endcase
   endfunction

  function [31:0] alu;
      input [4:0] opr, shift;
      input [31:0] operand1, operand2;
      case (opr)
        5'd0: alu = operand1 + operand2;
        5'd2: alu = operand1 - operand2;
        5'd8: alu = operand1 & operand2;
        5'd9: alu = operand1 | operand2;
        5'd10: alu = operand1 ^ operand2;
        5'd11: alu = ~ (operand1 & operand2);
        5'd16: alu = operand1 << shift; 
        5'd17: alu = operand1 >> shift;
        5'd18: alu = operand1 >>> shift;
        5'd20: alu = operand2 - operand1;  //追加
	      default: alu = 32'hffffffff;
      endcase
  endfunction

  function [31:0] calc;
      input [5:0]  op;
      input [31:0] alu_result, dpl_imm, dm_r_data, pc;
      case (op)
        6'd0, 6'd1, 6'd4, 6'd5, 6'd6, 6'd36: calc = alu_result; //36番の命令でaluの結果を使う
        6'd3: calc = dpl_imm << 16;
        6'd16: calc = dm_r_data;
        6'd18: calc = {{16{dm_r_data[15]}}, dm_r_data[15:0]};
        6'd20: calc = {{24{dm_r_data[7]}}, dm_r_data[7:0]};
        default: calc = 32'hffffffff;
      endcase
   endfunction

  function [31:0] npc;
      input [5:0]  op;
      input [31:0] reg1, reg2, branch, nonbranch, addr;
      case (op)
        6'd32: npc = (reg1 == reg2)? branch : nonbranch;
        6'd33: npc = (reg1 != reg2)? branch : nonbranch;
        6'd34: npc = (reg1 < reg2)? branch : nonbranch;
        6'd35: npc = (reg1 <= reg2)? branch : nonbranch;
		    6'd36: npc = (reg1 < reg2)? branch : nonbranch; // rt - rs > 0 より rs < rt
        6'd40, 6'd41: npc = addr;
        6'd42: npc = reg1;
        default: npc = nonbranch;
      endcase
  endfunction

  function [4:0] wreg;
      input [5:0]  op;
      input [4:0]  rt, rd;
      case (op)
        6'd0: wreg = rd;
        6'd1, 6'd3, 6'd4, 6'd5, 6'd6, 6'd16, 6'd18, 6'd20: wreg = rt;
		    6'd36: wreg = rt;
        6'd41: wreg = 5'd31;
        default: wreg = 5'd0;
      endcase
  endfunction

   function [3:0] wrengen;
      input [5:0]  op;
      case (op)
        6'd24: wrengen = 4'b0000;
        6'd26: wrengen = 4'b1100;
        6'd28: wrengen = 4'b1110;
        default: wrengen = 4'b1111;
      endcase
   endfunction

   assign op = ins [31:26] ;
   assign shift = ins [10:6] ;
   assign operation = ins [4:0] ;
   assign dpl_imm = {{16{ins[15]}} , ins [15:0]};
   assign operand2 = (op == 6'd0) ? reg2:((op == 6'd36) ? reg2 : dpl_imm); // 即値にrtをつかう．本当に??
   assign alu_result = alu (opr_gen (op, operation) , shift, reg1, operand2);
   assign mem_address = reg1 + dpl_imm >>> 2;
   assign wren = wrengen(op);
   data_mem data_mem_body0(mem_address[7:0], clk, reg2[7:0], wren[0], dm_r_data [7:0]);
   data_mem data_mem_body1(mem_address[7:0], clk, reg2[15:8], wren[1], dm_r_data[15:8]);
   data_mem data_mem_body2(mem_address[7:0], clk, reg2[23:16], wren[2], dm_r_data[23:16]);
   data_mem data_mem_body3(mem_address[7:0], clk, reg2[31:24], wren[3], dm_r_data[31:24]);
   assign wra = wreg(op, ins[20:16], ins[15:11]);
   assign result = calc (op, alu_result, dpl_imm, dm_r_data, pc);
   assign addr = ins[25:0];
   assign nonbranch = pc+32'd1; assign branch = nonbranch + dpl_imm;
   assign nextpc = npc(op, reg1, reg2, branch, nonbranch, addr);
endmodule

module data_mem(address, clk, write_data, wren, read_data);
   input [7:0] address;
   input       clk, wren;
   input [7:0] write_data;
   output [7:0] read_data;
   reg [7:0] 	d_mem [0:255] ;

   always @(posedge clk)
     if (wren == 0) d_mem[address] <= write_data;
   assign read_data = d_mem[address];
endmodule

module writeback(clk, rstd, nextpc, pc);
   input clk, rstd;
   input [31:0] nextpc;
   output [31:0] pc;
reg [31:0] pc;
   always @(negedge rstd or posedge clk)
     begin
	if (rstd == 0) pc <= 32'h00000000;
	  else if (clk == 1) pc <= nextpc;
     end
endmodule

module reg_file(clk, rstd, wr, ra1, ra2, wa, wren, rr1, rr2);
   input clk, rstd, wren;
   input [31:0] wr;
   input [4:0] 	ra1, ra2, wa;
   output [31:0] rr1, rr2;
   reg [31:0] 	 rf [0:31];
   assign rr1 = rf[ra1];
   assign rr2 = rf[ra2];
   always @(negedge rstd or posedge clk) begin
     if (rstd == 0) rf [0] <= 32'h00000000;
     else if (wren == 0) rf[wa] <= wr;
   end
endmodule

module computer(clk, rstd);
   input clk, rstd;
   wire [31:0] pc, ins, reg1, reg2, result, nextpc;
   wire [4:0]  wra;
   wire [3:0]  wren;
   fetch fetch_body (pc[7:0], ins);
   execute execute_body (clk, ins, pc, reg1, reg2, wra, result, nextpc);
   writeback writeback_body (clk, rstd, nextpc, pc);
   reg_file rf_body (clk, rstd, result, ins[25:21], ins[20:16], wra, (~| wra) , reg1, reg2);

  initial begin
    $monitor($time, ":rstd=%d, clk=%d, pc=%h, ins=%h, wra=%h, reg1=%h, reg2=%h, result=%h", rstd, clk, pc, ins, wra, reg1, reg2, result );
  end

endmodule

tb_computer.v
module tb_computer;
  
  reg clk, rstd;

  initial begin
    $dumpfile("cpu_35.vcd");
    $dumpvars;
    rstd = 1'b1;
    #10 rstd = 1'b0;
    #10 rstd = 1'b1;
    #10000 $finish;
  end

  initial begin
    clk = 0;
    forever #50 clk = ~clk;
  end

  // always begin
  //   #50 clk = ~clk;
  // end

  computer computer_0 (clk, rstd);

endmodule

cpu.vcd
$date
	Fri Jun 25 15:34:11 2021
$end
$version
	Icarus Verilog
$end
$timescale
	1s
$end
$scope module tb_computer $end
$var reg 1 ! clk $end
$var reg 1 " rstd $end
$scope module computer_0 $end
$var wire 1 ! clk $end
$var wire 1 " rstd $end
$var wire 5 # wra [4:0] $end
$var wire 32 $ result [31:0] $end
$var wire 32 % reg2 [31:0] $end
$var wire 32 & reg1 [31:0] $end
$var wire 32 ' pc [31:0] $end
$var wire 32 ( nextpc [31:0] $end
$var wire 32 ) ins [31:0] $end
$scope module execute_body $end
$var wire 1 ! clk $end
$var wire 4 * wren [3:0] $end
$var wire 5 + wra [4:0] $end
$var wire 5 , shift [4:0] $end
$var wire 32 - result [31:0] $end
$var wire 32 . reg2 [31:0] $end
$var wire 32 / reg1 [31:0] $end
$var wire 32 0 pc [31:0] $end
$var wire 5 1 operation [4:0] $end
$var wire 32 2 operand2 [31:0] $end
$var wire 6 3 op [5:0] $end
$var wire 32 4 nonbranch [31:0] $end
$var wire 32 5 nextpc [31:0] $end
$var wire 32 6 mem_address [31:0] $end
$var wire 32 7 ins [31:0] $end
$var wire 32 8 dpl_imm [31:0] $end
$var wire 32 9 dm_r_data [31:0] $end
$var wire 32 : branch [31:0] $end
$var wire 32 ; alu_result [31:0] $end
$var wire 26 < addr [25:0] $end
$scope function alu $end
$var reg 32 = alu [31:0] $end
$var reg 32 > operand1 [31:0] $end
$var reg 32 ? operand2 [31:0] $end
$var reg 5 @ opr [4:0] $end
$var reg 5 A shift [4:0] $end
$upscope $end
$scope function calc $end
$var reg 32 B alu_result [31:0] $end
$var reg 32 C calc [31:0] $end
$var reg 32 D dm_r_data [31:0] $end
$var reg 32 E dpl_imm [31:0] $end
$var reg 6 F op [5:0] $end
$var reg 32 G pc [31:0] $end
$upscope $end
$scope function npc $end
$var reg 32 H addr [31:0] $end
$var reg 32 I branch [31:0] $end
$var reg 32 J nonbranch [31:0] $end
$var reg 32 K npc [31:0] $end
$var reg 6 L op [5:0] $end
$var reg 32 M reg1 [31:0] $end
$var reg 32 N reg2 [31:0] $end
$upscope $end
$scope function opr_gen $end
$var reg 6 O op [5:0] $end
$var reg 5 P operation [4:0] $end
$var reg 5 Q opr_gen [4:0] $end
$upscope $end
$scope function wreg $end
$var reg 6 R op [5:0] $end
$var reg 5 S rd [4:0] $end
$var reg 5 T rt [4:0] $end
$var reg 5 U wreg [4:0] $end
$upscope $end
$scope function wrengen $end
$var reg 6 V op [5:0] $end
$var reg 4 W wrengen [3:0] $end
$upscope $end
$scope module data_mem_body0 $end
$var wire 8 X address [7:0] $end
$var wire 1 ! clk $end
$var wire 8 Y read_data [7:0] $end
$var wire 1 Z wren $end
$var wire 8 [ write_data [7:0] $end
$upscope $end
$scope module data_mem_body1 $end
$var wire 8 \ address [7:0] $end
$var wire 1 ! clk $end
$var wire 8 ] read_data [7:0] $end
$var wire 1 ^ wren $end
$var wire 8 _ write_data [7:0] $end
$upscope $end
$scope module data_mem_body2 $end
$var wire 8 ` address [7:0] $end
$var wire 1 ! clk $end
$var wire 8 a read_data [7:0] $end
$var wire 1 b wren $end
$var wire 8 c write_data [7:0] $end
$upscope $end
$scope module data_mem_body3 $end
$var wire 8 d address [7:0] $end
$var wire 1 ! clk $end
$var wire 8 e read_data [7:0] $end
$var wire 1 f wren $end
$var wire 8 g write_data [7:0] $end
$upscope $end
$upscope $end
$scope module fetch_body $end
$var wire 32 h ins [31:0] $end
$var wire 8 i pc [7:0] $end
$upscope $end
$scope module rf_body $end
$var wire 1 ! clk $end
$var wire 5 j ra1 [4:0] $end
$var wire 5 k ra2 [4:0] $end
$var wire 32 l rr1 [31:0] $end
$var wire 32 m rr2 [31:0] $end
$var wire 1 " rstd $end
$var wire 5 n wa [4:0] $end
$var wire 32 o wr [31:0] $end
$var wire 1 p wren $end
$upscope $end
$scope module writeback_body $end
$var wire 1 ! clk $end
$var wire 32 q nextpc [31:0] $end
$var wire 1 " rstd $end
$var reg 32 r pc [31:0] $end
$upscope $end
$upscope $end
$upscope $end
$enddefinitions $end
#0
$dumpvars
bx r
bx q
1p
b11111111111111111111111111111111 o
b0 n
bx m
bx l
bx k
bx j
bx i
bx h
bx g
1f
bx e
bx d
bx c
1b
bx a
bx `
bx _
1^
bx ]
bx \
bx [
1Z
bx Y
bx X
b1111 W
bx V
b0 U
bx T
bx S
bx R
b11111 Q
bx P
bx O
bx N
bx M
bx L
bx K
bx J
bx I
b0xxxxxxxxxxxxxxxxxxxxxxxxxx H
bx G
bx F
bx E
bx D
b11111111111111111111111111111111 C
b11111111111111111111111111111111 B
bx A
b11111 @
bx ?
bx >
b11111111111111111111111111111111 =
bx <
b11111111111111111111111111111111 ;
bx :
bx 9
bx 8
bx 7
b0xxxxxxxxxxxxxxxxxxxxxxxxxxxxxx 6
bx 5
bx 4
bx 3
bx 2
bx 1
bx 0
bx /
bx .
b11111111111111111111111111111111 -
bx ,
b0 +
b1111 *
bx )
bx (
bx '
bx &
bx %
b11111111111111111111111111111111 $
b0 #
1"
0!
$end
#10
b0 $
b0 -
b0 o
b0 C
b0 B
b0 X
b0 \
b0 `
b0 d
b0 ;
b0 =
b0 ?
b0 @
b0 6
b0 2
b0 Q
b0 P
b1 O
b1 V
0p
b1 #
b1 +
b1 n
b1 U
b0 S
b1 T
b1 R
b0 E
b1 F
b10000000000000000 H
b1 I
b0 M
b1 L
b0 >
b0 A
b10000000000000000 <
b1 :
b0 8
b0 1
b0 ,
b1 3
b1 k
b0 &
b0 /
b0 l
b0 j
b1 (
b1 5
b1 q
b1 K
b1 J
b0 G
b100000000010000000000000000 )
b100000000010000000000000000 7
b100000000010000000000000000 h
b0 i
b1 4
b0 '
b0 0
b0 r
0"
#20
1"
#50
b1 $
b1 -
b1 o
b1 C
b1 B
b1 ;
b1 =
b1 ?
b1 2
b10 #
b10 +
b10 n
b10 U
b10 T
b1 E
b1 P
b100000000000000001 H
b100000000000000001 <
b1 8
b1 1
b10 k
bx g
bx c
bx _
bx [
b10 (
b10 5
b10 q
b10 K
b10 J
b11 I
bx N
b1 G
b100000000100000000000000001 )
b100000000100000000000000001 7
b100000000100000000000000001 h
b1 i
bx %
bx .
bx m
b11 :
b10 4
b1 '
b1 0
b1 r
1!
#100
0!
#150
b10100 $
b10100 -
b10100 o
b10100 C
b10100 B
b10100 ;
b10100 =
b10100 ?
b10100 2
b101 X
b101 \
b101 `
b101 d
b11 #
b11 +
b11 n
b11 U
b11 T
b101 6
b10100 E
b10100 P
b110000000000010100 H
b110000000000010100 <
b10100 8
b10100 1
b11 k
b10 G
b100000000110000000000010100 )
b100000000110000000000010100 7
b100000000110000000000010100 h
b10 i
b11 (
b11 5
b11 q
b11 K
b11 J
b10111 I
bx N
bx g
bx c
bx _
bx [
b10111 :
b11 4
b10 '
b10 0
b10 r
bx %
bx .
bx m
1!
#200
0!
#250
b0 X
b0 \
b0 `
b0 d
b1000000000 6
b0 P
b0 O
b0 V
b1 #
b1 +
b1 n
b1 U
b1 S
b0 R
b100000000000 E
b0 F
b1000110000100000000000 H
b0 L
b1000110000100000000000 <
b100000000000 8
b0 1
b0 3
b1 j
b0 g
b0 c
b0 _
b10100 [
b100 (
b100 5
b100 q
b100 K
b100 J
b100000000100 I
b10100 N
b11 G
b1000110000100000000000 )
b1000110000100000000000 7
b1000110000100000000000 h
b11 i
b10100 %
b10100 .
b10100 m
b100000000100 :
b100 4
b11 '
b11 0
b11 r
1!
#300
0!
#350
b1 ?
b10 @
b11 #
b11 +
b11 n
b11 U
b11 S
b10 T
b1100000000010 E
b10 Q
b10 P
b11000100001100000000010 H
b1 N
b1 [
b1 2
b11000100001100000000010 <
b1100000000010 8
b10 1
b1 %
b1 .
b1 m
b10 k
b11 j
b101 X
b101 \
b101 `
b101 d
b10011 $
b10011 -
b10011 o
b10011 C
b100 G
b10011 B
b11000100001100000000010 )
b11000100001100000000010 7
b11000100001100000000010 h
b100 i
b101 (
b101 5
b101 q
b101 K
b101 J
b1100000000111 I
b10100 M
b11000000101 6
b10011 ;
b10011 =
b10100 >
b1100000000111 :
b101 4
b100 '
b100 0
b100 r
b10100 &
b10100 /
b10100 l
1!
#400
0!
#450
b11111111111111111111111111111101 ?
b11111 @
b11111111 X
b11111111 \
b11111111 `
b11111111 d
b11111 Q
b11101 P
b100010 O
b100010 V
1p
b0 #
b0 +
b0 n
b0 U
b11111 S
b11 T
b100010 R
b10011 [
b11111111111111111111111111111101 2
b111111111111111101 H
b10011 N
b100010 L
b111111111111111111111111111111 6
b11111 A
b11111111111111111111111111111111 $
b11111111111111111111111111111111 -
b11111111111111111111111111111111 o
b11111111111111111111111111111111 C
b11111111111111111111111111111101 E
b11111111111111111111111111111111 B
b100010 F
b111111111111111101 <
b11111111111111111111111111111101 8
b11101 1
b11111 ,
b100010 3
b10011 %
b10011 .
b10011 m
b11 k
b0 j
b11111111111111111111111111111111 ;
b11111111111111111111111111111111 =
b0 >
b11 (
b11 5
b11 q
b11 K
b110 J
b11 I
b0 M
b101 G
b10001000000000111111111111111101 )
b10001000000000111111111111111101 7
b10001000000000111111111111111101 h
b101 i
b0 &
b0 /
b0 l
b11 :
b110 4
b101 '
b101 0
b101 r
1!
#500
0!
#550
b100111 $
b100111 -
b100111 o
b100111 C
b100111 B
b100111 ;
b100111 =
b10011 ?
b0 @
b101 X
b101 \
b101 `
b101 d
b10011 2
b0 Q
b0 P
b0 O
b0 V
0p
b1 #
b1 +
b1 n
b1 U
b1 S
b0 R
b100000000000 E
b0 F
b1000110000100000000000 H
b10100 M
b0 L
b1000000101 6
b10100 >
b0 A
b1000110000100000000000 <
b100000000000 8
b0 1
b0 ,
b0 3
b10100 &
b10100 /
b10100 l
b1 j
b100 (
b100 5
b100 q
b100 K
b100 J
b100000000100 I
b11 G
b1000110000100000000000 )
b1000110000100000000000 7
b1000110000100000000000 h
b11 i
b100000000100 :
b100 4
b11 '
b11 0
b11 r
1!
#600
0!
#650
b1 ?
b10 @
b11 #
b11 +
b11 n
b11 U
b11 S
b10 T
b10 Q
b10 P
b1 [
b1 2
b11000100001100000000010 H
b1 N
b101 X
b101 \
b101 `
b101 d
b10010 $
b10010 -
b10010 o
b10010 C
b1100000000010 E
b10010 B
b11000100001100000000010 <
b1100000000010 8
b10 1
b1 %
b1 .
b1 m
b10 k
b11 j
b11000000101 6
b10010 ;
b10010 =
b10011 >
b101 (
b101 5
b101 q
b101 K
b101 J
b1100000000111 I
b10011 M
b100 G
b11000100001100000000010 )
b11000100001100000000010 7
b11000100001100000000010 h
b100 i
b10011 &
b10011 /
b10011 l
b1100000000111 :
b101 4
b100 '
b100 0
b100 r
1!
#700
0!
#750
b11111111111111111111111111111101 ?
b11111 @
b11111111 X
b11111111 \
b11111111 `
b11111111 d
b11111 Q
b11101 P
b100010 O
b100010 V
1p
b0 #
b0 +
b0 n
b0 U
b11111 S
b11 T
b100010 R
b11111111111111111111111111111101 E
b100010 F
b10010 [
b11111111111111111111111111111101 2
b111111111111111101 H
b10010 N
b100010 L
b111111111111111111111111111111 6
b11111 A
b111111111111111101 <
b11111111111111111111111111111101 8
b11101 1
b11111 ,
b100010 3
b10010 %
b10010 .
b10010 m
b11 k
b0 j
b11111111111111111111111111111111 $
b11111111111111111111111111111111 -
b11111111111111111111111111111111 o
b11111111111111111111111111111111 C
b101 G
b11111111111111111111111111111111 B
b10001000000000111111111111111101 )
b10001000000000111111111111111101 7
b10001000000000111111111111111101 h
b101 i
b11 (
b11 5
b11 q
b11 K
b110 J
b11 I
b0 M
b11111111111111111111111111111111 ;
b11111111111111111111111111111111 =
b0 >
b11 :
b110 4
b101 '
b101 0
b101 r
b0 &
b0 /
b0 l
1!
#800
0!
#850
b111001 $
b111001 -
b111001 o
b111001 C
b111001 B
b111001 ;
b111001 =
b10010 ?
b0 @
b1001 X
b1001 \
b1001 `
b1001 d
b10010 2
b0 Q
b0 P
b0 O
b0 V
0p
b1 #
b1 +
b1 n
b1 U
b1 S
b0 R
b100000000000 E
b0 F
b1000110000100000000000 H
b100111 M
b0 L
b1000001001 6
b100111 >
b0 A
b1000110000100000000000 <
b100000000000 8
b0 1
b0 ,
b0 3
b100111 &
b100111 /
b100111 l
b1 j
b100 (
b100 5
b100 q
b100 K
b100 J
b100000000100 I
b11 G
b1000110000100000000000 )
b1000110000100000000000 7
b1000110000100000000000 h
b11 i
b100000000100 :
b100 4
b11 '
b11 0
b11 r
1!
#900
0!
#950
b1 ?
b10 @
b11 #
b11 +
b11 n
b11 U
b11 S
b10 T
b1100000000010 E
b10 Q
b10 P
b1 [
b1 2
b11000100001100000000010 H
b1 N
b11000100001100000000010 <
b1100000000010 8
b10 1
b1 %
b1 .
b1 m
b10 k
b11 j
b101 X
b101 \
b101 `
b101 d
b10001 $
b10001 -
b10001 o
b10001 C
b100 G
b10001 B
b11000100001100000000010 )
b11000100001100000000010 7
b11000100001100000000010 h
b100 i
b101 (
b101 5
b101 q
b101 K
b101 J
b1100000000111 I
b10010 M
b11000000101 6
b10001 ;
b10001 =
b10010 >
b1100000000111 :
b101 4
b100 '
b100 0
b100 r
b10010 &
b10010 /
b10010 l
1!
#1000
0!
#1050
b11111111111111111111111111111101 ?
b11111 @
b11111 Q
b11101 P
b100010 O
b100010 V
1p
b0 #
b0 +
b0 n
b0 U
b11111 S
b11 T
b100010 R
b10001 [
b11111111111111111111111111111101 2
b111111111111111101 H
b10001 N
b100010 L
b11111 A
b11111111 X
b11111111 \
b11111111 `
b11111111 d
b11111111111111111111111111111111 $
b11111111111111111111111111111111 -
b11111111111111111111111111111111 o
b11111111111111111111111111111111 C
b11111111111111111111111111111101 E
b11111111111111111111111111111111 B
b100010 F
b111111111111111101 <
b11111111111111111111111111111101 8
b11101 1
b11111 ,
b100010 3
b10001 %
b10001 .
b10001 m
b11 k
b0 j
b111111111111111111111111111111 6
b11111111111111111111111111111111 ;
b11111111111111111111111111111111 =
b0 >
b11 (
b11 5
b11 q
b11 K
b110 J
b11 I
b0 M
b101 G
b10001000000000111111111111111101 )
b10001000000000111111111111111101 7
b10001000000000111111111111111101 h
b101 i
b0 &
b0 /
b0 l
b11 :
b110 4
b101 '
b101 0
b101 r
1!
#1100
0!
#1150
b1001010 $
b1001010 -
b1001010 o
b1001010 C
b1001010 B
b1001010 ;
b1001010 =
b10001 ?
b0 @
b1110 X
b1110 \
b1110 `
b1110 d
b10001 2
b0 Q
b0 P
b0 O
b0 V
0p
b1 #
b1 +
b1 n
b1 U
b1 S
b0 R
b100000000000 E
b0 F
b1000110000100000000000 H
b111001 M
b0 L
b1000001110 6
b111001 >
b0 A
b1000110000100000000000 <
b100000000000 8
b0 1
b0 ,
b0 3
b111001 &
b111001 /
b111001 l
b1 j
b100 (
b100 5
b100 q
b100 K
b100 J
b100000000100 I
b11 G
b1000110000100000000000 )
b1000110000100000000000 7
b1000110000100000000000 h
b11 i
b100000000100 :
b100 4
b11 '
b11 0
b11 r
1!
#1200
0!
#1250
b1 ?
b10 @
b11 #
b11 +
b11 n
b11 U
b11 S
b10 T
b10 Q
b10 P
b1 [
b1 2
b11000100001100000000010 H
b1 N
b100 X
b100 \
b100 `
b100 d
b10000 $
b10000 -
b10000 o
b10000 C
b1100000000010 E
b10000 B
b11000100001100000000010 <
b1100000000010 8
b10 1
b1 %
b1 .
b1 m
b10 k
b11 j
b11000000100 6
b10000 ;
b10000 =
b10001 >
b101 (
b101 5
b101 q
b101 K
b101 J
b1100000000111 I
b10001 M
b100 G
b11000100001100000000010 )
b11000100001100000000010 7
b11000100001100000000010 h
b100 i
b10001 &
b10001 /
b10001 l
b1100000000111 :
b101 4
b100 '
b100 0
b100 r
1!
#1300
0!
#1350
b11111111111111111111111111111101 ?
b11111 @
b11111111 X
b11111111 \
b11111111 `
b11111111 d
b11111 Q
b11101 P
b100010 O
b100010 V
1p
b0 #
b0 +
b0 n
b0 U
b11111 S
b11 T
b100010 R
b11111111111111111111111111111101 E
b100010 F
b10000 [
b11111111111111111111111111111101 2
b111111111111111101 H
b10000 N
b100010 L
b111111111111111111111111111111 6
b11111 A
b111111111111111101 <
b11111111111111111111111111111101 8
b11101 1
b11111 ,
b100010 3
b10000 %
b10000 .
b10000 m
b11 k
b0 j
b11111111111111111111111111111111 $
b11111111111111111111111111111111 -
b11111111111111111111111111111111 o
b11111111111111111111111111111111 C
b101 G
b11111111111111111111111111111111 B
b10001000000000111111111111111101 )
b10001000000000111111111111111101 7
b10001000000000111111111111111101 h
b101 i
b11 (
b11 5
b11 q
b11 K
b110 J
b11 I
b0 M
b11111111111111111111111111111111 ;
b11111111111111111111111111111111 =
b0 >
b11 :
b110 4
b101 '
b101 0
b101 r
b0 &
b0 /
b0 l
1!
#1400
0!
#1450
b1011010 $
b1011010 -
b1011010 o
b1011010 C
b1011010 B
b1011010 ;
b1011010 =
b10000 ?
b0 @
b10010 X
b10010 \
b10010 `
b10010 d
b10000 2
b0 Q
b0 P
b0 O
b0 V
0p
b1 #
b1 +
b1 n
b1 U
b1 S
b0 R
b100000000000 E
b0 F
b1000110000100000000000 H
b1001010 M
b0 L
b1000010010 6
b1001010 >
b0 A
b1000110000100000000000 <
b100000000000 8
b0 1
b0 ,
b0 3
b1001010 &
b1001010 /
b1001010 l
b1 j
b100 (
b100 5
b100 q
b100 K
b100 J
b100000000100 I
b11 G
b1000110000100000000000 )
b1000110000100000000000 7
b1000110000100000000000 h
b11 i
b100000000100 :
b100 4
b11 '
b11 0
b11 r
1!
#1500
0!
#1550
b1 ?
b10 @
b11 #
b11 +
b11 n
b11 U
b11 S
b10 T
b1100000000010 E
b10 Q
b10 P
b1 [
b1 2
b11000100001100000000010 H
b1 N
b11000100001100000000010 <
b1100000000010 8
b10 1
b1 %
b1 .
b1 m
b10 k
b11 j
b100 X
b100 \
b100 `
b100 d
b1111 $
b1111 -
b1111 o
b1111 C
b100 G
b1111 B
b11000100001100000000010 )
b11000100001100000000010 7
b11000100001100000000010 h
b100 i
b101 (
b101 5
b101 q
b101 K
b101 J
b1100000000111 I
b10000 M
b11000000100 6
b1111 ;
b1111 =
b10000 >
b1100000000111 :
b101 4
b100 '
b100 0
b100 r
b10000 &
b10000 /
b10000 l
1!
#1600
0!
#1650
b11111111111111111111111111111101 ?
b11111 @
b11111111 X
b11111111 \
b11111111 `
b11111111 d
b11111 Q
b11101 P
b100010 O
b100010 V
1p
b0 #
b0 +
b0 n
b0 U
b11111 S
b11 T
b100010 R
b1111 [
b11111111111111111111111111111101 2
b111111111111111101 H
b1111 N
b100010 L
b111111111111111111111111111111 6
b11111 A
b11111111111111111111111111111111 $
b11111111111111111111111111111111 -
b11111111111111111111111111111111 o
b11111111111111111111111111111111 C
b11111111111111111111111111111101 E
b11111111111111111111111111111111 B
b100010 F
b111111111111111101 <
b11111111111111111111111111111101 8
b11101 1
b11111 ,
b100010 3
b1111 %
b1111 .
b1111 m
b11 k
b0 j
b11111111111111111111111111111111 ;
b11111111111111111111111111111111 =
b0 >
b11 (
b11 5
b11 q
b11 K
b110 J
b11 I
b0 M
b101 G
b10001000000000111111111111111101 )
b10001000000000111111111111111101 7
b10001000000000111111111111111101 h
b101 i
b0 &
b0 /
b0 l
b11 :
b110 4
b101 '
b101 0
b101 r
1!
#1700
0!
#1750
b1101001 $
b1101001 -
b1101001 o
b1101001 C
b1101001 B
b1101001 ;
b1101001 =
b1111 ?
b0 @
b10110 X
b10110 \
b10110 `
b10110 d
b1111 2
b0 Q
b0 P
b0 O
b0 V
0p
b1 #
b1 +
b1 n
b1 U
b1 S
b0 R
b100000000000 E
b0 F
b1000110000100000000000 H
b1011010 M
b0 L
b1000010110 6
b1011010 >
b0 A
b1000110000100000000000 <
b100000000000 8
b0 1
b0 ,
b0 3
b1011010 &
b1011010 /
b1011010 l
b1 j
b100 (
b100 5
b100 q
b100 K
b100 J
b100000000100 I
b11 G
b1000110000100000000000 )
b1000110000100000000000 7
b1000110000100000000000 h
b11 i
b100000000100 :
b100 4
b11 '
b11 0
b11 r
1!
#1800
0!
#1850
b1 ?
b10 @
b11 #
b11 +
b11 n
b11 U
b11 S
b10 T
b10 Q
b10 P
b1 [
b1 2
b11000100001100000000010 H
b1 N
b100 X
b100 \
b100 `
b100 d
b1110 $
b1110 -
b1110 o
b1110 C
b1100000000010 E
b1110 B
b11000100001100000000010 <
b1100000000010 8
b10 1
b1 %
b1 .
b1 m
b10 k
b11 j
b11000000100 6
b1110 ;
b1110 =
b1111 >
b101 (
b101 5
b101 q
b101 K
b101 J
b1100000000111 I
b1111 M
b100 G
b11000100001100000000010 )
b11000100001100000000010 7
b11000100001100000000010 h
b100 i
b1111 &
b1111 /
b1111 l
b1100000000111 :
b101 4
b100 '
b100 0
b100 r
1!
#1900
0!
#1950
b11111111111111111111111111111101 ?
b11111 @
b11111111 X
b11111111 \
b11111111 `
b11111111 d
b11111 Q
b11101 P
b100010 O
b100010 V
1p
b0 #
b0 +
b0 n
b0 U
b11111 S
b11 T
b100010 R
b11111111111111111111111111111101 E
b100010 F
b1110 [
b11111111111111111111111111111101 2
b111111111111111101 H
b1110 N
b100010 L
b111111111111111111111111111111 6
b11111 A
b111111111111111101 <
b11111111111111111111111111111101 8
b11101 1
b11111 ,
b100010 3
b1110 %
b1110 .
b1110 m
b11 k
b0 j
b11111111111111111111111111111111 $
b11111111111111111111111111111111 -
b11111111111111111111111111111111 o
b11111111111111111111111111111111 C
b101 G
b11111111111111111111111111111111 B
b10001000000000111111111111111101 )
b10001000000000111111111111111101 7
b10001000000000111111111111111101 h
b101 i
b11 (
b11 5
b11 q
b11 K
b110 J
b11 I
b0 M
b11111111111111111111111111111111 ;
b11111111111111111111111111111111 =
b0 >
b11 :
b110 4
b101 '
b101 0
b101 r
b0 &
b0 /
b0 l
1!
#2000
0!
#2050
b1110111 $
b1110111 -
b1110111 o
b1110111 C
b1110111 B
b1110111 ;
b1110111 =
b1110 ?
b0 @
b11010 X
b11010 \
b11010 `
b11010 d
b1110 2
b0 Q
b0 P
b0 O
b0 V
0p
b1 #
b1 +
b1 n
b1 U
b1 S
b0 R
b100000000000 E
b0 F
b1000110000100000000000 H
b1101001 M
b0 L
b1000011010 6
b1101001 >
b0 A
b1000110000100000000000 <
b100000000000 8
b0 1
b0 ,
b0 3
b1101001 &
b1101001 /
b1101001 l
b1 j
b100 (
b100 5
b100 q
b100 K
b100 J
b100000000100 I
b11 G
b1000110000100000000000 )
b1000110000100000000000 7
b1000110000100000000000 h
b11 i
b100000000100 :
b100 4
b11 '
b11 0
b11 r
1!
#2100
0!
