cpu.v
module fetch (pc, ins);
  input [7:0] pc;   //32bitの値はでかすぎるだろ
  output [31:0] ins;
  reg [31:0] ins_mem[0:255];
  assign ins = ins_mem[pc];
  initial begin
    // $readmemb("sample34.bnr", ins_mem);
    $readmemb("add.bnr", ins_mem);

  end
endmodule

module execute (clk, ins, pc, reg1, reg2, wra, result, nextpc);
	input clk;
	input [31:0] ins, pc, reg1, reg2;
	output [4:0] wra;
	output [31:0] result, nextpc;
	wire [5:0] 	 op;
	wire [4:0] 	 shift, operation;
	wire [25:0] 	 addr;
	wire [31:0] 	 dpl_imm, operand2, alu_result, nonbranch, branch, mem_address, dm_r_data;
	wire [3:0] 	 wren;

  	function [4:0] opr_gen; 	// 出力にどんな演算結果を渡すのかを決める(加算，減算など)
		input [5:0] op;        
		input [4:0] operation;
		case (op)				//　アセンブラで指定した命令番号について場合分け
			6'd0: opr_gen = operation;
			6'd1: opr_gen = 5'd0;	// add
			6'd4: opr_gen = 5'd8;	// and
			6'd5: opr_gen = 5'd9;	// or
			6'd6: opr_gen = 5'd10;	// xor
			6'd36: opr_gen = 5'd20;  // sub, bgt0_subはop36番
			default: opr_gen = 5'h1f;
		endcase
   endfunction

  function [31:0] alu;
      input [4:0] opr, shift;
      input [31:0] operand1, operand2;
      case (opr)
        5'd0: alu = operand1 + operand2;
        5'd2: alu = operand1 - operand2;
        5'd8: alu = operand1 & operand2;
        5'd9: alu = operand1 | operand2;
        5'd10: alu = operand1 ^ operand2;
        5'd11: alu = ~ (operand1 & operand2);
        5'd16: alu = operand1 << shift;
        5'd17: alu = operand1 >> shift;
        5'd18: alu = operand1 >>> shift;
        5'd20: alu = operand2 - operand1;  //追加
	      default: alu = 32'hffffffff;
      endcase
  endfunction

  function [31:0] calc;
      input [5:0]  op;
      input [31:0] alu_result, dpl_imm, dm_r_data, pc;
      case (op)
        6'd0, 6'd1, 6'd4, 6'd5, 6'd6, 6'd36: calc = alu_result; //36番の命令でaluの結果を使う
        6'd3: calc = dpl_imm << 16;
        6'd16: calc = dm_r_data;
        6'd18: calc = {{16{dm_r_data[15]}}, dm_r_data[15:0]};
        6'd20: calc = {{24{dm_r_data[7]}}, dm_r_data[7:0]};
        default: calc = 32'hffffffff;
      endcase
   endfunction

  function [31:0] npc;
      input [5:0]  op;
      input [31:0] reg1, reg2, branch, nonbranch, addr;
      case (op)
        6'd32: npc = (reg1 == reg2)? branch : nonbranch;
        6'd33: npc = (reg1 != reg2)? branch : nonbranch;
        6'd34: npc = (reg1 < reg2)? branch : nonbranch;
        6'd35: npc = (reg1 <= reg2)? branch : nonbranch;
		    6'd36: npc = (reg1 < reg2)? branch : nonbranch; // rt - rs > 0 より rs < rt
        6'd40, 6'd41: npc = addr;
        6'd42: npc = reg1;
        default: npc = nonbranch;
      endcase
  endfunction

  function [4:0] wreg;
      input [5:0]  op;
      input [4:0]  rt, rd;
      case (op)
        6'd0: wreg = rd;
        6'd1, 6'd3, 6'd4, 6'd5, 6'd6, 6'd16, 6'd18, 6'd20: wreg = rt;
		    6'd36: wreg = rt;
        6'd41: wreg = 5'd31;
        default: wreg = 5'd0;
      endcase
  endfunction

   function [3:0] wrengen;
      input [5:0]  op;
      case (op)
        6'd24: wrengen = 4'b0000;
        6'd26: wrengen = 4'b1100;
        6'd28: wrengen = 4'b1110;
        default: wrengen = 4'b1111;
      endcase
   endfunction

   assign op = ins [31:26] ;
   assign shift = ins [10:6] ;
   assign operation = ins [4:0] ;
   assign dpl_imm = {{16{ins[15]}} , ins [15:0]};
   assign operand2 = (op == 6'd0) ? reg2:((op == 6'd36) ? reg2 : dpl_imm); // 即値にrtをつかう．本当に??
   assign alu_result = alu (opr_gen (op, operation) , shift, reg1, operand2);
   assign mem_address = reg1 + dpl_imm >>> 2;
   assign wren = wrengen(op);
   data_mem data_mem_body0(mem_address[7:0], clk, reg2[7:0], wren[0], dm_r_data [7:0]);
   data_mem data_mem_body1(mem_address[7:0], clk, reg2[15:8], wren[1], dm_r_data[15:8]);
   data_mem data_mem_body2(mem_address[7:0], clk, reg2[23:16], wren[2], dm_r_data[23:16]);
   data_mem data_mem_body3(mem_address[7:0], clk, reg2[31:24], wren[3], dm_r_data[31:24]);
   assign wra = wreg(op, ins[20:16], ins[15:11]);
   assign result = calc (op, alu_result, dpl_imm, dm_r_data, pc);
   assign addr = ins[25:0];
   assign nonbranch = pc+32'd1; assign branch = nonbranch + dpl_imm;
   assign nextpc = npc(op, reg1, reg2, branch, nonbranch, addr);
endmodule

module data_mem(address, clk, write_data, wren, read_data);
   input [7:0] address;
   input       clk, wren;
   input [7:0] write_data;
   output [7:0] read_data;
   reg [7:0] 	d_mem [0:255] ;

   always @(posedge clk)
     if (wren == 0) d_mem[address] <= write_data;
   assign read_data = d_mem[address];
endmodule

module writeback(clk, rstd, nextpc, pc);
   input clk, rstd;
   input [31:0] nextpc;
   output [31:0] pc;
reg [31:0] pc;
   always @(negedge rstd or posedge clk)
     begin
	if (rstd == 0) pc <= 32'h00000000;
	  else if (clk == 1) pc <= nextpc;
     end
endmodule

module reg_file(clk, rstd, wr, ra1, ra2, wa, wren, rr1, rr2);
   input clk, rstd, wren;
   input [31:0] wr;
   input [4:0] 	ra1, ra2, wa;
   output [31:0] rr1, rr2;
   reg [31:0] 	 rf [0:31];
   assign rr1 = rf[ra1];
   assign rr2 = rf[ra2];
   always @(negedge rstd or posedge clk) begin
     if (rstd == 0) rf [0] <= 32'h00000000;
     else if (wren == 0) rf[wa] <= wr;
   end
endmodule

module computer(clk, rstd);
   input clk, rstd;
   wire [31:0] pc, ins, reg1, reg2, result, nextpc;
   wire [4:0]  wra;
   wire [3:0]  wren;
   fetch fetch_body (pc[7:0], ins);
   execute execute_body (clk, ins, pc, reg1, reg2, wra, result, nextpc);
   writeback writeback_body (clk, rstd, nextpc, pc);
   reg_file rf_body (clk, rstd, result, ins[25:21], ins[20:16], wra, (~| wra) , reg1, reg2);

  initial begin
    $monitor($time, ":rstd=%d, clk=%d, pc=%h, ins=%h, wra=%h, reg1=%h, reg2=%h", rstd, clk, pc, ins, wra, reg1, reg2);
  end

endmodule

tb_computer.v
module tb_computer;
  
  reg clk, rstd;

  initial begin
    rstd = 1'b1;
    #10 rstd = 1'b0;
    #10 rstd = 1'b1;
  end

  initial begin
    $dumpfile("cpu.vcd");
    $dumpvars;
    clk = 0;
    // forever #50 clk = ~clk;
    #10000 $finish;
  end

  always begin
    #50 clk = ~clk;
  end

  computer computer_0 (clk, rstd);

endmodule

cpu.vcd
$date
	Thu Jun 24 23:38:15 2021
$end
$version
	Icarus Verilog
$end
$timescale
	1s
$end
$scope module tb_computer $end
$var reg 1 ! clk $end
$var reg 1 " rstd $end
$scope module computer_0 $end
$var wire 1 ! clk $end
$var wire 1 " rstd $end
$var wire 5 # wra [4:0] $end
$var wire 32 $ result [31:0] $end
$var wire 32 % reg2 [31:0] $end
$var wire 32 & reg1 [31:0] $end
$var wire 32 ' pc [31:0] $end
$var wire 32 ( nextpc [31:0] $end
$var wire 32 ) ins [31:0] $end
$scope module execute_body $end
$var wire 1 ! clk $end
$var wire 4 * wren [3:0] $end
$var wire 5 + wra [4:0] $end
$var wire 5 , shift [4:0] $end
$var wire 32 - result [31:0] $end
$var wire 32 . reg2 [31:0] $end
$var wire 32 / reg1 [31:0] $end
$var wire 32 0 pc [31:0] $end
$var wire 5 1 operation [4:0] $end
$var wire 32 2 operand2 [31:0] $end
$var wire 6 3 op [5:0] $end
$var wire 32 4 nonbranch [31:0] $end
$var wire 32 5 nextpc [31:0] $end
$var wire 32 6 mem_address [31:0] $end
$var wire 32 7 ins [31:0] $end
$var wire 32 8 dpl_imm [31:0] $end
$var wire 32 9 dm_r_data [31:0] $end
$var wire 32 : branch [31:0] $end
$var wire 32 ; alu_result [31:0] $end
$var wire 26 < addr [25:0] $end
$scope function alu $end
$var reg 32 = alu [31:0] $end
$var reg 32 > operand1 [31:0] $end
$var reg 32 ? operand2 [31:0] $end
$var reg 5 @ opr [4:0] $end
$var reg 5 A shift [4:0] $end
$upscope $end
$scope function calc $end
$var reg 32 B alu_result [31:0] $end
$var reg 32 C calc [31:0] $end
$var reg 32 D dm_r_data [31:0] $end
$var reg 32 E dpl_imm [31:0] $end
$var reg 6 F op [5:0] $end
$var reg 32 G pc [31:0] $end
$upscope $end
$scope function npc $end
$var reg 32 H addr [31:0] $end
$var reg 32 I branch [31:0] $end
$var reg 32 J nonbranch [31:0] $end
$var reg 32 K npc [31:0] $end
$var reg 6 L op [5:0] $end
$var reg 32 M reg1 [31:0] $end
$var reg 32 N reg2 [31:0] $end
$upscope $end
$scope function opr_gen $end
$var reg 6 O op [5:0] $end
$var reg 5 P operation [4:0] $end
$var reg 5 Q opr_gen [4:0] $end
$upscope $end
$scope function wreg $end
$var reg 6 R op [5:0] $end
$var reg 5 S rd [4:0] $end
$var reg 5 T rt [4:0] $end
$var reg 5 U wreg [4:0] $end
$upscope $end
$scope function wrengen $end
$var reg 6 V op [5:0] $end
$var reg 4 W wrengen [3:0] $end
$upscope $end
$scope module data_mem_body0 $end
$var wire 8 X address [7:0] $end
$var wire 1 ! clk $end
$var wire 8 Y read_data [7:0] $end
$var wire 1 Z wren $end
$var wire 8 [ write_data [7:0] $end
$upscope $end
$scope module data_mem_body1 $end
$var wire 8 \ address [7:0] $end
$var wire 1 ! clk $end
$var wire 8 ] read_data [7:0] $end
$var wire 1 ^ wren $end
$var wire 8 _ write_data [7:0] $end
$upscope $end
$scope module data_mem_body2 $end
$var wire 8 ` address [7:0] $end
$var wire 1 ! clk $end
$var wire 8 a read_data [7:0] $end
$var wire 1 b wren $end
$var wire 8 c write_data [7:0] $end
$upscope $end
$scope module data_mem_body3 $end
$var wire 8 d address [7:0] $end
$var wire 1 ! clk $end
$var wire 8 e read_data [7:0] $end
$var wire 1 f wren $end
$var wire 8 g write_data [7:0] $end
$upscope $end
$upscope $end
$scope module fetch_body $end
$var wire 32 h ins [31:0] $end
$var wire 8 i pc [7:0] $end
$upscope $end
$scope module rf_body $end
$var wire 1 ! clk $end
$var wire 5 j ra1 [4:0] $end
$var wire 5 k ra2 [4:0] $end
$var wire 32 l rr1 [31:0] $end
$var wire 32 m rr2 [31:0] $end
$var wire 1 " rstd $end
$var wire 5 n wa [4:0] $end
$var wire 32 o wr [31:0] $end
$var wire 1 p wren $end
$upscope $end
$scope module writeback_body $end
$var wire 1 ! clk $end
$var wire 32 q nextpc [31:0] $end
$var wire 1 " rstd $end
$var reg 32 r pc [31:0] $end
$upscope $end
$upscope $end
$upscope $end
$enddefinitions $end
#0
$dumpvars
bx r
bx q
1p
b11111111111111111111111111111111 o
b0 n
bx m
bx l
bx k
bx j
bx i
bx h
bx g
1f
bx e
bx d
bx c
1b
bx a
bx `
bx _
1^
bx ]
bx \
bx [
1Z
bx Y
bx X
b1111 W
bx V
b0 U
bx T
bx S
bx R
b11111 Q
bx P
bx O
bx N
bx M
bx L
bx K
bx J
bx I
b0xxxxxxxxxxxxxxxxxxxxxxxxxx H
bx G
bx F
bx E
bx D
b11111111111111111111111111111111 C
b11111111111111111111111111111111 B
bx A
b11111 @
bx ?
bx >
b11111111111111111111111111111111 =
bx <
b11111111111111111111111111111111 ;
bx :
bx 9
bx 8
bx 7
b0xxxxxxxxxxxxxxxxxxxxxxxxxxxxxx 6
bx 5
bx 4
bx 3
bx 2
bx 1
bx 0
bx /
bx .
b11111111111111111111111111111111 -
bx ,
b0 +
b1111 *
bx )
bx (
bx '
bx &
bx %
b11111111111111111111111111111111 $
b0 #
1"
0!
$end
#10
b1 $
b1 -
b1 o
b1 C
b1 B
b0 X
b0 \
b0 `
b0 d
b1 ;
b1 =
b1 ?
b0 @
b0 6
b1 2
b0 Q
b1 P
b1 O
b1 V
0p
b1 #
b1 +
b1 n
b1 U
b0 S
b1 T
b1 R
b1 E
b1 F
b10000000000000001 H
b10 I
b0 M
b1 L
b0 >
b0 A
b10000000000000001 <
b10 :
b1 8
b1 1
b0 ,
b1 3
b1 k
b0 &
b0 /
b0 l
b0 j
b1 (
b1 5
b1 q
b1 K
b1 J
b0 G
b100000000010000000000000001 )
b100000000010000000000000001 7
b100000000010000000000000001 h
b0 i
b1 4
b0 '
b0 0
b0 r
0"
#20
1"
#50
b10 $
b10 -
b10 o
b10 C
b10 B
b10 #
b10 +
b10 n
b10 U
b10 T
b1000100000000000000001 H
b1 M
b10 ;
b10 =
b1 >
b1000100000000000000001 <
b10 k
b1 &
b1 /
b1 l
b1 j
bx g
bx c
bx _
bx [
b10 (
b10 5
b10 q
b10 K
b10 J
b11 I
bx N
b1 G
b100001000100000000000000001 )
b100001000100000000000000001 7
b100001000100000000000000001 h
b1 i
bx %
bx .
bx m
b11 :
b10 4
b1 '
b1 0
b1 r
1!
#100
0!
#150
bx ?
b11111 @
bx X
bx \
bx `
bx d
bx 2
b11111 Q
bx P
bx O
bx V
1p
b0 #
b0 +
b0 n
b0 U
bx S
bx T
bx R
b11111111111111111111111111111111 $
b11111111111111111111111111111111 -
b11111111111111111111111111111111 o
b11111111111111111111111111111111 C
bx E
b11111111111111111111111111111111 B
bx F
b0xxxxxxxxxxxxxxxxxxxxxxxxxx H
bx M
bx L
b0xxxxxxxxxxxxxxxxxxxxxxxxxxxxxx 6
b11111111111111111111111111111111 ;
b11111111111111111111111111111111 =
bx >
bx A
bx <
bx 8
bx 1
bx ,
bx 3
bx k
bx &
bx /
bx l
bx j
b10 G
bx )
bx 7
bx h
b10 i
b11 (
b11 5
b11 q
b11 K
b11 J
bx I
bx N
bx g
bx c
bx _
bx [
bx :
b11 4
b10 '
b10 0
b10 r
bx %
bx .
bx m
1!
#200
0!
#250
b100 (
b100 5
b100 q
b100 K
b100 J
b11 G
b11 i
b100 4
b11 '
b11 0
b11 r
1!
#300
0!
#350
b101 (
b101 5
b101 q
b101 K
b101 J
b100 G
b100 i
b101 4
b100 '
b100 0
b100 r
1!
#400
0!
#450
b110 (
b110 5
b110 q
b110 K
b110 J
b101 G
b101 i
b110 4
b101 '
b101 0
b101 r
1!
#500
0!
#550
b111 (
b111 5
b111 q
b111 K
b111 J
b110 G
b110 i
b111 4
b110 '
b110 0
b110 r
1!
#600
0!
#650
b1000 (
b1000 5
b1000 q
b1000 K
b1000 J
b111 G
b111 i
b1000 4
b111 '
b111 0
b111 r
1!
#700
0!
#750
b1001 (
b1001 5
b1001 q
b1001 K
b1001 J
b1000 G
b1000 i
b1001 4
b1000 '
b1000 0
b1000 r
1!
#800
0!
#850
b1010 (
b1010 5
b1010 q
b1010 K
b1010 J
b1001 G
b1001 i
b1010 4
b1001 '
b1001 0
b1001 r
1!
#900
0!
#950
b1011 (
b1011 5
b1011 q
b1011 K
b1011 J
b1010 G
b1010 i
b1011 4
b1010 '
b1010 0
b1010 r
1!
#1000
0!
#1050
b1100 (
b1100 5
b1100 q
b1100 K
b1100 J
b1011 G
b1011 i
b1100 4
b1011 '
b1011 0
b1011 r
1!
#1100
0!
#1150
b1101 (
b1101 5
b1101 q
b1101 K
b1101 J
b1100 G
b1100 i
b1101 4
b1100 '
b1100 0
b1100 r
1!
#1200
0!
#1250
b1110 (
b1110 5
b1110 q
b1110 K
b1110 J
b1101 G
b1101 i
b1110 4
b1101 '
b1101 0
b1101 r
1!
#1300
0!
#1350
b1111 (
b1111 5
b1111 q
b1111 K
b1111 J
b1110 G
b1110 i
b1111 4
b1110 '
b1110 0
b1110 r
1!
#1400
0!
#1450
b10000 (
b10000 5
b10000 q
b10000 K
b10000 J
b1111 G
b1111 i
b10000 4
b1111 '
b1111 0
b1111 r
1!
#1500
0!
#1550
b10001 (
b10001 5
b10001 q
b10001 K
b10001 J
b10000 G
b10000 i
b10001 4
b10000 '
b10000 0
b10000 r
1!
#1600
0!
#1650
b10010 (
b10010 5
b10010 q
b10010 K
b10010 J
b10001 G
b10001 i
b10010 4
b10001 '
b10001 0
b10001 r
1!
#1700
0!
#1750
b10011 (
b10011 5
b10011 q
b10011 K
b10011 J
b10010 G
b10010 i
b10011 4
b10010 '
b10010 0
b10010 r
1!
#1800
0!
#1850
b10100 (
b10100 5
b10100 q
b10100 K
b10100 J
b10011 G
b10011 i
b10100 4
b10011 '
b10011 0
b10011 r
1!
#1900
0!
#1950
b10101 (
b10101 5
b10101 q
b10101 K
b10101 J
b10100 G
b10100 i
b10101 4
b10100 '
b10100 0
b10100 r
1!
#2000
0!
#2050
b10110 (
b10110 5
b10110 q
b10110 K
b10110 J
b10101 G
b10101 i
b10110 4
b10101 '
b10101 0
b10101 r
1!
#2100
0!
#2150
b10111 (
b10111 5
b10111 q
b10111 K
b10111 J
b10110 G
b10110 i
b10111 4
b10110 '
b10110 0
b10110 r
1!
#2200
0!
#2250
b11000 (
b11000 5
b11000 q
b11000 K
b11000 J
b10111 G
b10111 i
b11000 4
b10111 '
b10111 0
b10111 r
1!
#2300
0!
#2350
b11001 (
b11001 5
b11001 q
b11001 K
b11001 J
b11000 G
b11000 i
b11001 4
b11000 '
b11000 0
b11000 r
1!
#2400
0!
#2450
b11010 (
b11010 5
b11010 q
b11010 K
b11010 J
b11001 G
b11001 i
b11010 4
b11001 '
b11001 0
b11001 r
1!
#2500
0!
#2550
b11011 (
b11011 5
b11011 q
b11011 K
b11011 J
b11010 G
b11010 i
b11011 4
b11010 '
b11010 0
b11010 r
1!
#2600
0!
#2650
b11100 (
b11100 5
b11100 q
b11100 K
b11100 J
b11011 G
b11011 i
b11100 4
b11011 '
b11011 0
b11011 r
1!
#2700
0!
#2750
b11101 (
b11101 5
b11101 q
b11101 K
b11101 J
b11100 G
b11100 i
b11101 4
b11100 '
b11100 0
b11100 r
1!
#2800
0!
#2850
b11110 (
b11110 5
b11110 q
b11110 K
b11110 J
b11101 G
b11101 i
b11110 4
b11101 '
b11101 0
b11101 r
1!
#2900
0!
#2950
b11111 (
b11111 5
b11111 q
b11111 K
b11111 J
b11110 G
b11110 i
b11111 4
b11110 '
b11110 0
b11110 r
1!
#3000
0!
#3050
b100000 (
b100000 5
b100000 q
b100000 K
b100000 J
b11111 G
b11111 i
b100000 4
b11111 '
b11111 0
b11111 r
1!
#3100
0!
#3150
b100001 (
b100001 5
b100001 q
b100001 K
b100001 J
b100000 G
b100000 i
b100001 4
b100000 '
b100000 0
b100000 r
1!
#3200
0!
#3250
b100010 (
b100010 5
b100010 q
b100010 K
b100010 J
b100001 G
b100001 i
b100010 4
b100001 '
b100001 0
b100001 r
1!
#3300
0!
#3350
b100011 (
b100011 5
b100011 q
b100011 K
b100011 J
b100010 G
b100010 i
b100011 4
b100010 '
b100010 0
b100010 r
1!
#3400
0!
#3450
b100100 (
b100100 5
b100100 q
b100100 K
b100100 J
b100011 G
b100011 i
b100100 4
b100011 '
b100011 0
b100011 r
1!
#3500
0!
#3550
b100101 (
b100101 5
b100101 q
b100101 K
b100101 J
b100100 G
b100100 i
b100101 4
b100100 '
b100100 0
b100100 r
1!
#3600
0!
#3650
b100110 (
b100110 5
b100110 q
b100110 K
b100110 J
b100101 G
b100101 i
b100110 4
b100101 '
b100101 0
b100101 r
1!
#3700
0!
#3750
b100111 (
b100111 5
b100111 q
b100111 K
b100111 J
b100110 G
b100110 i
b100111 4
b100110 '
b100110 0
b100110 r
1!
#3800
0!
#3850
b101000 (
b101000 5
b101000 q
b101000 K
b101000 J
b100111 G
b100111 i
b101000 4
b100111 '
b100111 0
b100111 r
1!
#3900
0!
#3950
b101001 (
b101001 5
b101001 q
b101001 K
b101001 J
b101000 G
b101000 i
b101001 4
b101000 '
b101000 0
b101000 r
1!
#4000
0!
#4050
b101010 (
b101010 5
b101010 q
b101010 K
b101010 J
b101001 G
b101001 i
b101010 4
b101001 '
b101001 0
b101001 r
1!
#4100
0!
#4150
b101011 (
b101011 5
b101011 q
b101011 K
b101011 J
b101010 G
b101010 i
b101011 4
b101010 '
b101010 0
b101010 r
1!
#4200
0!
#4250
b101100 (
b101100 5
b101100 q
b101100 K
b101100 J
b101011 G
b101011 i
b101100 4
b101011 '
b101011 0
b101011 r
1!
#4300
0!
#4350
b101101 (
b101101 5
b101101 q
b101101 K
b101101 J
b101100 G
b101100 i
b101101 4
b101100 '
b101100 0
b101100 r
1!
#4400
0!
#4450
b101110 (
b101110 5
b101110 q
b101110 K
b101110 J
b101101 G
b101101 i
b101110 4
b101101 '
b101101 0
b101101 r
1!
#4500
0!
#4550
b101111 (
b101111 5
b101111 q
b101111 K
b101111 J
b101110 G
b101110 i
b101111 4
b101110 '
b101110 0
b101110 r
1!
#4600
0!
#4650
b110000 (
b110000 5
b110000 q
b110000 K
b110000 J
b101111 G
b101111 i
b110000 4
b101111 '
b101111 0
b101111 r
1!
#4700
0!
#4750
b110001 (
b110001 5
b110001 q
b110001 K
b110001 J
b110000 G
b110000 i
b110001 4
b110000 '
b110000 0
b110000 r
1!
#4800
0!
#4850
b110010 (
b110010 5
b110010 q
b110010 K
b110010 J
b110001 G
b110001 i
b110010 4
b110001 '
b110001 0
b110001 r
1!
#4900
0!
#4950
b110011 (
b110011 5
b110011 q
b110011 K
b110011 J
b110010 G
b110010 i
b110011 4
b110010 '
b110010 0
b110010 r
1!
#5000
0!
#5050
b110100 (
b110100 5
b110100 q
b110100 K
b110100 J
b110011 G
b110011 i
b110100 4
b110011 '
b110011 0
b110011 r
1!
#5100
0!
#5150
b110101 (
b110101 5
b110101 q
b110101 K
b110101 J
b110100 G
b110100 i
b110101 4
b110100 '
b110100 0
b110100 r
1!
#5200
0!
#5250
b110110 (
b110110 5
b110110 q
b110110 K
b110110 J
b110101 G
b110101 i
b110110 4
b110101 '
b110101 0
b110101 r
1!
#5300
0!
#5350
b110111 (
b110111 5
b110111 q
b110111 K
b110111 J
b110110 G
b110110 i
b110111 4
b110110 '
b110110 0
b110110 r
1!
#5400
0!
#5450
b111000 (
b111000 5
b111000 q
b111000 K
b111000 J
b110111 G
b110111 i
b111000 4
b110111 '
b110111 0
b110111 r
1!
#5500
0!
#5550
b111001 (
b111001 5
b111001 q
b111001 K
b111001 J
b111000 G
b111000 i
b111001 4
b111000 '
b111000 0
b111000 r
1!
#5600
0!
#5650
b111010 (
b111010 5
b111010 q
b111010 K
b111010 J
b111001 G
b111001 i
b111010 4
b111001 '
b111001 0
b111001 r
1!
#5700
0!
#5750
b111011 (
b111011 5
b111011 q
b111011 K
b111011 J
b111010 G
b111010 i
b111011 4
b111010 '
b111010 0
b111010 r
1!
#5800
0!
#5850
b111100 (
b111100 5
b111100 q
b111100 K
b111100 J
b111011 G
b111011 i
b111100 4
b111011 '
b111011 0
b111011 r
1!
#5900
0!
#5950
b111101 (
b111101 5
b111101 q
b111101 K
b111101 J
b111100 G
b111100 i
b111101 4
b111100 '
b111100 0
b111100 r
1!
#6000
0!
#6050
b111110 (
b111110 5
b111110 q
b111110 K
b111110 J
b111101 G
b111101 i
b111110 4
b111101 '
b111101 0
b111101 r
1!
#6100
0!
#6150
b111111 (
b111111 5
b111111 q
b111111 K
b111111 J
b111110 G
b111110 i
b111111 4
b111110 '
b111110 0
b111110 r
1!
#6200
0!
#6250
b1000000 (
b1000000 5
b1000000 q
b1000000 K
b1000000 J
b111111 G
b111111 i
b1000000 4
b111111 '
b111111 0
b111111 r
1!
#6300
0!
#6350
b1000001 (
b1000001 5
b1000001 q
b1000001 K
b1000001 J
b1000000 G
b1000000 i
b1000001 4
b1000000 '
b1000000 0
b1000000 r
1!
#6400
0!
#6450
b1000010 (
b1000010 5
b1000010 q
b1000010 K
b1000010 J
b1000001 G
b1000001 i
b1000010 4
b1000001 '
b1000001 0
b1000001 r
1!
#6500
0!
#6550
b1000011 (
b1000011 5
b1000011 q
b1000011 K
b1000011 J
b1000010 G
b1000010 i
b1000011 4
b1000010 '
b1000010 0
b1000010 r
1!
#6600
0!
#6650
b1000100 (
b1000100 5
b1000100 q
b1000100 K
b1000100 J
b1000011 G
b1000011 i
b1000100 4
b1000011 '
b1000011 0
b1000011 r
1!
#6700
0!
#6750
b1000101 (
b1000101 5
b1000101 q
b1000101 K
b1000101 J
b1000100 G
b1000100 i
b1000101 4
b1000100 '
b1000100 0
b1000100 r
1!
#6800
0!
#6850
b1000110 (
b1000110 5
b1000110 q
b1000110 K
b1000110 J
b1000101 G
b1000101 i
b1000110 4
b1000101 '
b1000101 0
b1000101 r
1!
#6900
0!
#6950
b1000111 (
b1000111 5
b1000111 q
b1000111 K
b1000111 J
b1000110 G
b1000110 i
b1000111 4
b1000110 '
b1000110 0
b1000110 r
1!
#7000
0!
#7050
b1001000 (
b1001000 5
b1001000 q
b1001000 K
b1001000 J
b1000111 G
b1000111 i
b1001000 4
b1000111 '
b1000111 0
b1000111 r
1!
#7100
0!
#7150
b1001001 (
b1001001 5
b1001001 q
b1001001 K
b1001001 J
b1001000 G
b1001000 i
b1001001 4
b1001000 '
b1001000 0
b1001000 r
1!
#7200
0!
#7250
b1001010 (
b1001010 5
b1001010 q
b1001010 K
b1001010 J
b1001001 G
b1001001 i
b1001010 4
b1001001 '
b1001001 0
b1001001 r
1!
#7300
0!
#7350
b1001011 (
b1001011 5
b1001011 q
b1001011 K
b1001011 J
b1001010 G
b1001010 i
b1001011 4
b1001010 '
b1001010 0
b1001010 r
1!
#7400
0!
#7450
b1001100 (
b1001100 5
b1001100 q
b1001100 K
b1001100 J
b1001011 G
b1001011 i
b1001100 4
b1001011 '
b1001011 0
b1001011 r
1!
#7500
0!
#7550
b1001101 (
b1001101 5
b1001101 q
b1001101 K
b1001101 J
b1001100 G
b1001100 i
b1001101 4
b1001100 '
b1001100 0
b1001100 r
1!
#7600
0!
#7650
b1001110 (
b1001110 5
b1001110 q
b1001110 K
b1001110 J
b1001101 G
b1001101 i
b1001110 4
b1001101 '
b1001101 0
b1001101 r
1!
#7700
0!
#7750
b1001111 (
b1001111 5
b1001111 q
b1001111 K
b1001111 J
b1001110 G
b1001110 i
b1001111 4
b1001110 '
b1001110 0
b1001110 r
1!
#7800
0!
#7850
b1010000 (
b1010000 5
b1010000 q
b1010000 K
b1010000 J
b1001111 G
b1001111 i
b1010000 4
b1001111 '
b1001111 0
b1001111 r
1!
#7900
0!
#7950
b1010001 (
b1010001 5
b1010001 q
b1010001 K
b1010001 J
b1010000 G
b1010000 i
b1010001 4
b1010000 '
b1010000 0
b1010000 r
1!
#8000
0!
#8050
b1010010 (
b1010010 5
b1010010 q
b1010010 K
b1010010 J
b1010001 G
b1010001 i
b1010010 4
b1010001 '
b1010001 0
b1010001 r
1!
#8100
0!
#8150
b1010011 (
b1010011 5
b1010011 q
b1010011 K
b1010011 J
b1010010 G
b1010010 i
b1010011 4
b1010010 '
b1010010 0
b1010010 r
1!
#8200
0!
#8250
b1010100 (
b1010100 5
b1010100 q
b1010100 K
b1010100 J
b1010011 G
b1010011 i
b1010100 4
b1010011 '
b1010011 0
b1010011 r
1!
#8300
0!
#8350
b1010101 (
b1010101 5
b1010101 q
b1010101 K
b1010101 J
b1010100 G
b1010100 i
b1010101 4
b1010100 '
b1010100 0
b1010100 r
1!
#8400
0!
#8450
b1010110 (
b1010110 5
b1010110 q
b1010110 K
b1010110 J
b1010101 G
b1010101 i
b1010110 4
b1010101 '
b1010101 0
b1010101 r
1!
#8500
0!
#8550
b1010111 (
b1010111 5
b1010111 q
b1010111 K
b1010111 J
b1010110 G
b1010110 i
b1010111 4
b1010110 '
b1010110 0
b1010110 r
1!
#8600
0!
#8650
b1011000 (
b1011000 5
b1011000 q
b1011000 K
b1011000 J
b1010111 G
b1010111 i
b1011000 4
b1010111 '
b1010111 0
b1010111 r
1!
#8700
0!
#8750
b1011001 (
b1011001 5
b1011001 q
b1011001 K
b1011001 J
b1011000 G
b1011000 i
b1011001 4
b1011000 '
b1011000 0
b1011000 r
1!
#8800
0!
#8850
b1011010 (
b1011010 5
b1011010 q
b1011010 K
b1011010 J
b1011001 G
b1011001 i
b1011010 4
b1011001 '
b1011001 0
b1011001 r
1!
#8900
0!
#8950
b1011011 (
b1011011 5
b1011011 q
b1011011 K
b1011011 J
b1011010 G
b1011010 i
b1011011 4
b1011010 '
b1011010 0
b1011010 r
1!
#9000
0!
#9050
b1011100 (
b1011100 5
b1011100 q
b1011100 K
b1011100 J
b1011011 G
b1011011 i
b1011100 4
b1011011 '
b1011011 0
b1011011 r
1!
#9100
0!
#9150
b1011101 (
b1011101 5
b1011101 q
b1011101 K
b1011101 J
b1011100 G
b1011100 i
b1011101 4
b1011100 '
b1011100 0
b1011100 r
1!
#9200
0!
#9250
b1011110 (
b1011110 5
b1011110 q
b1011110 K
b1011110 J
b1011101 G
b1011101 i
b1011110 4
b1011101 '
b1011101 0
b1011101 r
1!
#9300
0!
#9350
b1011111 (
b1011111 5
b1011111 q
b1011111 K
b1011111 J
b1011110 G
b1011110 i
b1011111 4
b1011110 '
b1011110 0
b1011110 r
1!
#9400
0!
#9450
b1100000 (
b1100000 5
b1100000 q
b1100000 K
b1100000 J
b1011111 G
b1011111 i
b1100000 4
b1011111 '
b1011111 0
b1011111 r
1!
#9500
0!
#9550
b1100001 (
b1100001 5
b1100001 q
b1100001 K
b1100001 J
b1100000 G
b1100000 i
b1100001 4
b1100000 '
b1100000 0
b1100000 r
1!
#9600
0!
#9650
b1100010 (
b1100010 5
b1100010 q
b1100010 K
b1100010 J
b1100001 G
b1100001 i
b1100010 4
b1100001 '
b1100001 0
b1100001 r
1!
#9700
0!
#9750
b1100011 (
b1100011 5
b1100011 q
b1100011 K
b1100011 J
b1100010 G
b1100010 i
b1100011 4
b1100010 '
b1100010 0
b1100010 r
1!
#9800
0!
#9850
b1100100 (
b1100100 5
b1100100 q
b1100100 K
b1100100 J
b1100011 G
b1100011 i
b1100100 4
b1100011 '
b1100011 0
b1100011 r
1!
